Tensorflow1XShenduXuexiMijiChuyiFix1/README.md
Tensorflow1XShenduXuexiMijiChuyiFix1/__init__.py
Tensorflow1XShenduXuexiMijiChuyiFix1/__main__.py
Tensorflow1XShenduXuexiMijiChuyiFix1/file.epub
Tensorflow1XShenduXuexiMijiChuyiFix1/index.html
Tensorflow1XShenduXuexiMijiChuyiFix1/css/__init__.py
Tensorflow1XShenduXuexiMijiChuyiFix1/css/annotations.css
Tensorflow1XShenduXuexiMijiChuyiFix1/css/main.css
Tensorflow1XShenduXuexiMijiChuyiFix1/css/normalize.css
Tensorflow1XShenduXuexiMijiChuyiFix1/css/popup.css
Tensorflow1XShenduXuexiMijiChuyiFix1/font/__init__.py
Tensorflow1XShenduXuexiMijiChuyiFix1/font/fontello.eot
Tensorflow1XShenduXuexiMijiChuyiFix1/font/fontello.svg
Tensorflow1XShenduXuexiMijiChuyiFix1/font/fontello.ttf
Tensorflow1XShenduXuexiMijiChuyiFix1/font/fontello.woff
Tensorflow1XShenduXuexiMijiChuyiFix1/img/__init__.py
Tensorflow1XShenduXuexiMijiChuyiFix1/img/annotator-glyph-sprite.png
Tensorflow1XShenduXuexiMijiChuyiFix1/img/annotator-icon-sprite.png
Tensorflow1XShenduXuexiMijiChuyiFix1/img/apple-touch-icon.png
Tensorflow1XShenduXuexiMijiChuyiFix1/img/cancelfullscreen.png
Tensorflow1XShenduXuexiMijiChuyiFix1/img/close.png
Tensorflow1XShenduXuexiMijiChuyiFix1/img/fullscreen.png
Tensorflow1XShenduXuexiMijiChuyiFix1/img/loader.gif
Tensorflow1XShenduXuexiMijiChuyiFix1/img/menu-icon.png
Tensorflow1XShenduXuexiMijiChuyiFix1/img/save.png
Tensorflow1XShenduXuexiMijiChuyiFix1/img/saved.png
Tensorflow1XShenduXuexiMijiChuyiFix1/img/settings-s.png
Tensorflow1XShenduXuexiMijiChuyiFix1/img/settings.png
Tensorflow1XShenduXuexiMijiChuyiFix1/img/star.png
Tensorflow1XShenduXuexiMijiChuyiFix1/js/__init__.py
Tensorflow1XShenduXuexiMijiChuyiFix1/js/epub.js
Tensorflow1XShenduXuexiMijiChuyiFix1/js/epub.min.js
Tensorflow1XShenduXuexiMijiChuyiFix1/js/epub.min.map
Tensorflow1XShenduXuexiMijiChuyiFix1/js/hooks.min.js
Tensorflow1XShenduXuexiMijiChuyiFix1/js/hooks.min.map
Tensorflow1XShenduXuexiMijiChuyiFix1/js/reader.js
Tensorflow1XShenduXuexiMijiChuyiFix1/js/reader.js.map
tensorflow_1_x_shendu_xuexi_miji_chuyi_fix1-2025.3.24.1.dist-info/METADATA
tensorflow_1_x_shendu_xuexi_miji_chuyi_fix1-2025.3.24.1.dist-info/WHEEL
tensorflow_1_x_shendu_xuexi_miji_chuyi_fix1-2025.3.24.1.dist-info/entry_points.txt
tensorflow_1_x_shendu_xuexi_miji_chuyi_fix1-2025.3.24.1.dist-info/top_level.txt
tensorflow_1_x_shendu_xuexi_miji_chuyi_fix1-2025.3.24.1.dist-info/RECORD
